[
  {
    "id": "6660_0_2021",
    "vehicle": "Skoda Fabia1.0 TSI Active Cool Plus",
    "price": 6660,
    "km": 0,
    "year": 2021,
    "fuel": "diesel",
    "source": "marketplace",
    "link": "https://www.autoscout24.de/angebote/skoda-fabia-1-0-tsi-active-cool-plus-benzin-schwarz-c4c90a5d-4eec-4796-9b25-3068326c92f4",
    "notes": "🔴 AutoScout Achado Kastenwagen <7k",
    "score": 100,
    "addedAt": "2026-03-21T10:20:16.423817"
  },
  {
    "id": "6990_0_2021",
    "vehicle": "Opel CorsaF GS AUTOMATIK STARTET NCIHT",
    "price": 6990,
    "km": 0,
    "year": 2021,
    "fuel": "diesel",
    "source": "marketplace",
    "link": "https://www.autoscout24.de/angebote/opel-corsa-f-gs-automatik-startet-nciht-benzin-grau-713647b1-36a7-4b03-9d0d-e1d5c057ab19",
    "notes": "🔴 AutoScout Achado Kastenwagen <7k",
    "score": 100,
    "addedAt": "2026-03-21T10:16:06.903595"
  },
  {
    "id": "5690_0_2021",
    "vehicle": "Dacia SpringElectric Comfort Plus 33 KW, EU6, Kamera",
    "price": 5690,
    "km": 0,
    "year": 2021,
    "fuel": "diesel",
    "source": "marketplace",
    "link": "https://www.autoscout24.de/angebote/dacia-spring-electric-comfort-plus-33-kw-eu6-kamera-elektro-grau-6cfcc600-9a86-4b74-82fc-996dee5478f5",
    "notes": "🔴 AutoScout Achado Kastenwagen <7k",
    "score": 100,
    "addedAt": "2026-03-21T10:09:49.464710"
  },
  {
    "id": "6890_0_2021",
    "vehicle": "Volkswagen up!up!",
    "price": 6890,
    "km": 0,
    "year": 2021,
    "fuel": "diesel",
    "source": "marketplace",
    "link": "https://www.autoscout24.de/angebote/volkswagen-up-up-benzin-76687a09-58c5-4d75-bbd0-8264f49cc3fa",
    "notes": "🔴 AutoScout Achado Kastenwagen <7k",
    "score": 100,
    "addedAt": "2026-03-21T10:07:44.349389"
  },
  {
    "id": "4990_0_2021",
    "vehicle": "Fiat Tipo1.0  City Sport #MOTORSCHADEN#",
    "price": 4990,
    "km": 0,
    "year": 2021,
    "fuel": "diesel",
    "source": "marketplace",
    "link": "https://www.autoscout24.de/angebote/fiat-tipo-1-0-city-sport-motorschaden-benzin-grau-5e19a8ce-ea03-42d9-9a51-e70d453d0877",
    "notes": "🔴 AutoScout Achado Kastenwagen <7k",
    "score": 100,
    "addedAt": "2026-03-21T10:07:44.348866"
  },
  {
    "id": "1700_0_2021",
    "vehicle": "Opel CorsaF GS Line, 1.2  74 KW",
    "price": 1700,
    "km": 0,
    "year": 2021,
    "fuel": "diesel",
    "source": "marketplace",
    "link": "https://www.autoscout24.de/angebote/opel-corsa-f-gs-line-1-2-74-kw-benzin-schwarz-9c39ed6b-1f4e-49d7-9eb1-98966f802a70",
    "notes": "🔴 AutoScout Achado Kastenwagen <7k",
    "score": 100,
    "addedAt": "2026-03-21T10:07:44.348866"
  },
  {
    "id": "4000_0_2021",
    "vehicle": "Dacia SpringElectric Comfort Plus",
    "price": 4000,
    "km": 0,
    "year": 2021,
    "fuel": "diesel",
    "source": "marketplace",
    "link": "https://www.autoscout24.de/angebote/dacia-spring-electric-comfort-plus-elektro-silber-b852098c-1adc-40e2-970d-ecfe6f5f88d6",
    "notes": "🔴 AutoScout Achado Kastenwagen <7k",
    "score": 100,
    "addedAt": "2026-03-21T10:07:44.347326"
  },
  {
    "id": "6900_0_2021",
    "vehicle": "smart forFour smart forfour electric drive EQ",
    "price": 6900,
    "km": 0,
    "year": 2021,
    "fuel": "diesel",
    "source": "marketplace",
    "link": "",
    "notes": "🔴 AutoScout Achado Kastenwagen <7k",
    "score": 100,
    "addedAt": "2026-03-21T10:07:44.347326"
  },
  {
    "id": "3500_0_2021",
    "vehicle": "Volkswagen Polo 1.2 Goal",
    "price": 3500,
    "km": 0,
    "year": 2021,
    "fuel": "diesel",
    "source": "marketplace",
    "link": "",
    "notes": "🔴 AutoScout Achado Kastenwagen <7k",
    "score": 100,
    "addedAt": "2026-03-21T10:07:44.346311"
  },
  {
    "id": "5300_0_2021",
    "vehicle": "SEAT Ibiza SC 1.0 Eco TSI S&S FR",
    "price": 5300,
    "km": 0,
    "year": 2021,
    "fuel": "diesel",
    "source": "marketplace",
    "link": "",
    "notes": "🔴 AutoScout Achado Kastenwagen <7k",
    "score": 100,
    "addedAt": "2026-03-21T10:07:44.345313"
  },
  {
    "id": "5500_0_2021",
    "vehicle": "Mercedes-Benz C 240 C 240 Avantgarde",
    "price": 5500,
    "km": 0,
    "year": 2021,
    "fuel": "diesel",
    "source": "marketplace",
    "link": "",
    "notes": "🔴 AutoScout Achado Kastenwagen <7k",
    "score": 100,
    "addedAt": "2026-03-21T10:07:44.345313"
  },
  {
    "id": "6400_0_2021",
    "vehicle": "Renault Twingo Techno Electric/AUT/NAV/R-KAM/TEMP",
    "price": 6400,
    "km": 0,
    "year": 2021,
    "fuel": "diesel",
    "source": "marketplace",
    "link": "",
    "notes": "🔴 AutoScout Achado Kastenwagen <7k",
    "score": 100,
    "addedAt": "2026-03-21T10:07:44.344310"
  },
  {
    "id": "6980_0_2021",
    "vehicle": "Citroen C1 FEEL KLIMAANLAGE   1. BESITZ",
    "price": 6980,
    "km": 0,
    "year": 2021,
    "fuel": "diesel",
    "source": "marketplace",
    "link": "",
    "notes": "🔴 AutoScout Achado Kastenwagen <7k",
    "score": 100,
    "addedAt": "2026-03-21T10:07:44.344310"
  },
  {
    "id": "3699_0_2021",
    "vehicle": "Dacia Sandero Sandero 1.2 16V 75 Ambiance",
    "price": 3699,
    "km": 0,
    "year": 2021,
    "fuel": "diesel",
    "source": "marketplace",
    "link": "",
    "notes": "🔴 AutoScout Achado Kastenwagen <7k",
    "score": 100,
    "addedAt": "2026-03-21T10:07:44.343205"
  },
  {
    "id": "6900_0_2021",
    "vehicle": "Volkswagen up! Up  5-Türer white style-Klima-SHZ- Tempomat",
    "price": 6900,
    "km": 0,
    "year": 2021,
    "fuel": "diesel",
    "source": "marketplace",
    "link": "",
    "notes": "🔴 AutoScout Achado Kastenwagen <7k",
    "score": 100,
    "addedAt": "2026-03-21T10:07:44.343205"
  },
  {
    "id": "7000_0_2021",
    "vehicle": "Mitsubishi Space Star AS&G 1.2 Spirit+ Black",
    "price": 7000,
    "km": 0,
    "year": 2021,
    "fuel": "diesel",
    "source": "marketplace",
    "link": "",
    "notes": "🔴 AutoScout Achado Kastenwagen <7k",
    "score": 92,
    "addedAt": "2026-03-21T10:07:44.346311"
  },
  {
    "id": "9888_0_2021",
    "vehicle": "Dacia Spring Comfort KLIMA DAB BT ZV",
    "price": 9888,
    "km": 0,
    "year": 2021,
    "fuel": "diesel",
    "source": "marketplace",
    "link": "",
    "notes": "🔴 AutoScout Achado Kastenwagen <7k",
    "score": 77,
    "addedAt": "2026-03-21T10:43:38.256547"
  },
  {
    "id": "8990_0_2021",
    "vehicle": "Ford Fiesta Cool & Connect",
    "price": 8990,
    "km": 0,
    "year": 2021,
    "fuel": "diesel",
    "source": "marketplace",
    "link": "",
    "notes": "🔴 AutoScout Achado Kastenwagen <7k",
    "score": 77,
    "addedAt": "2026-03-21T10:34:41.290191"
  },
  {
    "id": "8900_0_2021",
    "vehicle": "smart forFour 60kW EQ Batterie",
    "price": 8900,
    "km": 0,
    "year": 2021,
    "fuel": "diesel",
    "source": "marketplace",
    "link": "",
    "notes": "🔴 AutoScout Achado Kastenwagen <7k",
    "score": 77,
    "addedAt": "2026-03-21T10:30:24.041504"
  },
  {
    "id": "9450_0_2021",
    "vehicle": "smart forFour EQ  PASSION+WINTERPAKET+SHZ+LENKRADHZ",
    "price": 9450,
    "km": 0,
    "year": 2021,
    "fuel": "diesel",
    "source": "marketplace",
    "link": "",
    "notes": "🔴 AutoScout Achado Kastenwagen <7k",
    "score": 77,
    "addedAt": "2026-03-21T10:28:11.634199"
  },
  {
    "id": "9980_0_2021",
    "vehicle": "Renault Clio V 1.0 SCe 65 Life LED+SpurH+SpurW",
    "price": 9980,
    "km": 0,
    "year": 2021,
    "fuel": "diesel",
    "source": "marketplace",
    "link": "",
    "notes": "🔴 AutoScout Achado Kastenwagen <7k",
    "score": 77,
    "addedAt": "2026-03-21T10:27:08.240718"
  },
  {
    "id": "10990_0_2021",
    "vehicle": "Opel Corsa Edition*Klima*PDC*Bluetooth*Lichtsensor*",
    "price": 10990,
    "km": 0,
    "year": 2021,
    "fuel": "diesel",
    "source": "marketplace",
    "link": "",
    "notes": "🔴 AutoScout Achado Kastenwagen <7k",
    "score": 77,
    "addedAt": "2026-03-21T10:26:06.249070"
  },
  {
    "id": "10650_0_2021",
    "vehicle": "Opel Corsa F 1.2 Edition",
    "price": 10650,
    "km": 0,
    "year": 2021,
    "fuel": "diesel",
    "source": "marketplace",
    "link": "",
    "notes": "🔴 AutoScout Achado Kastenwagen <7k",
    "score": 77,
    "addedAt": "2026-03-21T10:26:06.248567"
  },
  {
    "id": "14425_0_2021",
    "vehicle": "Opel Corsa Elegance 1.2 *Navi/Sitzheiz/Parkpilot*",
    "price": 14425,
    "km": 0,
    "year": 2021,
    "fuel": "diesel",
    "source": "marketplace",
    "link": "",
    "notes": "🔴 AutoScout Achado Kastenwagen <7k",
    "score": 52,
    "addedAt": "2026-03-21T13:26:28.378048"
  },
  {
    "id": "13890_0_2021",
    "vehicle": "Dacia Spring ELECTRIC EXTREME 65 CCS INKL.BATTERIE",
    "price": 13890,
    "km": 0,
    "year": 2021,
    "fuel": "diesel",
    "source": "marketplace",
    "link": "",
    "notes": "🔴 AutoScout Achado Kastenwagen <7k",
    "score": 52,
    "addedAt": "2026-03-21T13:26:28.378048"
  },
  {
    "id": "14890_0_2021",
    "vehicle": "Mitsubishi Space Star Select 1.2 MIVEC 5-Gang",
    "price": 14890,
    "km": 0,
    "year": 2021,
    "fuel": "diesel",
    "source": "marketplace",
    "link": "",
    "notes": "🔴 AutoScout Achado Kastenwagen <7k",
    "score": 52,
    "addedAt": "2026-03-21T13:26:28.377546"
  },
  {
    "id": "13390_0_2021",
    "vehicle": "Fiat Panda Mild Hybrid City Paket  Gelato Weiß",
    "price": 13390,
    "km": 0,
    "year": 2021,
    "fuel": "diesel",
    "source": "marketplace",
    "link": "",
    "notes": "🔴 AutoScout Achado Kastenwagen <7k",
    "score": 52,
    "addedAt": "2026-03-21T13:25:26.041818"
  },
  {
    "id": "14450_0_2021",
    "vehicle": "Volkswagen e-up! e-up! SHZ KLIMA ALU",
    "price": 14450,
    "km": 0,
    "year": 2021,
    "fuel": "diesel",
    "source": "marketplace",
    "link": "",
    "notes": "🔴 AutoScout Achado Kastenwagen <7k",
    "score": 52,
    "addedAt": "2026-03-21T13:25:26.041818"
  },
  {
    "id": "12350_0_2021",
    "vehicle": "Citroen C3 1.2 Puretech*Einparkhilfe*Klima",
    "price": 12350,
    "km": 0,
    "year": 2021,
    "fuel": "diesel",
    "source": "marketplace",
    "link": "",
    "notes": "🔴 AutoScout Achado Kastenwagen <7k",
    "score": 52,
    "addedAt": "2026-03-21T13:25:26.041818"
  },
  {
    "id": "12865_0_2021",
    "vehicle": "Suzuki Swift Club 1.2 Dualjet DAB/Klima/BT/Isofix/Assis",
    "price": 12865,
    "km": 0,
    "year": 2021,
    "fuel": "diesel",
    "source": "marketplace",
    "link": "",
    "notes": "🔴 AutoScout Achado Kastenwagen <7k",
    "score": 52,
    "addedAt": "2026-03-21T13:25:26.039816"
  },
  {
    "id": "12990_0_2021",
    "vehicle": "Ford Focus Active 1.0 EcoBoost Mild-Hybrid EU6d",
    "price": 12990,
    "km": 0,
    "year": 2021,
    "fuel": "diesel",
    "source": "marketplace",
    "link": "",
    "notes": "🔴 AutoScout Achado Kastenwagen <7k",
    "score": 52,
    "addedAt": "2026-03-21T13:25:26.039314"
  },
  {
    "id": "14444_0_2021",
    "vehicle": "Renault ZOE Intens R135 incl. Batterie+51kW+NAVI+CAM+LED",
    "price": 14444,
    "km": 0,
    "year": 2021,
    "fuel": "diesel",
    "source": "marketplace",
    "link": "",
    "notes": "🔴 AutoScout Achado Kastenwagen <7k",
    "score": 52,
    "addedAt": "2026-03-21T13:24:23.744442"
  },
  {
    "id": "14351_0_2021",
    "vehicle": "Skoda Fabia 1.0 TSI Active LED PDC SHZ SpurH Winterp.",
    "price": 14351,
    "km": 0,
    "year": 2021,
    "fuel": "diesel",
    "source": "marketplace",
    "link": "",
    "notes": "🔴 AutoScout Achado Kastenwagen <7k",
    "score": 52,
    "addedAt": "2026-03-21T13:24:23.744442"
  },
  {
    "id": "14950_0_2021",
    "vehicle": "Citroen C3 1.2 PureTech 110 MAX Navi LED Apple CarPlay Androi",
    "price": 14950,
    "km": 0,
    "year": 2021,
    "fuel": "diesel",
    "source": "marketplace",
    "link": "",
    "notes": "🔴 AutoScout Achado Kastenwagen <7k",
    "score": 52,
    "addedAt": "2026-03-21T13:24:23.742675"
  },
  {
    "id": "14940_0_2021",
    "vehicle": "MG MG3 1.5 116PS Standard Navi Klima CarPlay SOFORT",
    "price": 14940,
    "km": 0,
    "year": 2021,
    "fuel": "diesel",
    "source": "marketplace",
    "link": "",
    "notes": "🔴 AutoScout Achado Kastenwagen <7k",
    "score": 52,
    "addedAt": "2026-03-21T13:24:23.741170"
  },
  {
    "id": "14990_0_2021",
    "vehicle": "Dacia Sandero TCe 100 Stepway Essential KLIMA",
    "price": 14990,
    "km": 0,
    "year": 2021,
    "fuel": "diesel",
    "source": "marketplace",
    "link": "",
    "notes": "🔴 AutoScout Achado Kastenwagen <7k",
    "score": 52,
    "addedAt": "2026-03-21T13:24:23.741170"
  },
  {
    "id": "12970_0_2021",
    "vehicle": "Ford Fiesta 1.0 Cool&Connect AppLink|Tempom.|LED",
    "price": 12970,
    "km": 0,
    "year": 2021,
    "fuel": "diesel",
    "source": "marketplace",
    "link": "",
    "notes": "🔴 AutoScout Achado Kastenwagen <7k",
    "score": 52,
    "addedAt": "2026-03-21T13:23:21.283104"
  },
  {
    "id": "13080_0_2021",
    "vehicle": "Renault Clio V EQUILIBRE TCE 90 CARPLAY SHZ PDC KLIMA",
    "price": 13080,
    "km": 0,
    "year": 2021,
    "fuel": "diesel",
    "source": "marketplace",
    "link": "",
    "notes": "🔴 AutoScout Achado Kastenwagen <7k",
    "score": 52,
    "addedAt": "2026-03-21T13:23:21.282049"
  },
  {
    "id": "12490_0_2021",
    "vehicle": "Peugeot 308 Active Pack PT130 Einparkhilfe SHZ ACC PDC",
    "price": 12490,
    "km": 0,
    "year": 2021,
    "fuel": "diesel",
    "source": "marketplace",
    "link": "",
    "notes": "🔴 AutoScout Achado Kastenwagen <7k",
    "score": 52,
    "addedAt": "2026-03-21T13:22:19.090303"
  },
  {
    "id": "12749_0_2021",
    "vehicle": "Opel Corsa e Edition 5-Türer NAV+180°+SHZ+TEMPO+16ZO",
    "price": 12749,
    "km": 0,
    "year": 2021,
    "fuel": "diesel",
    "source": "marketplace",
    "link": "",
    "notes": "🔴 AutoScout Achado Kastenwagen <7k",
    "score": 52,
    "addedAt": "2026-03-21T13:21:16.643171"
  },
  {
    "id": "14984_0_2021",
    "vehicle": "Opel Corsa F Elegance NAVI/APP~AHK~SHZ~2xPDC~LED~DAB",
    "price": 14984,
    "km": 0,
    "year": 2021,
    "fuel": "diesel",
    "source": "marketplace",
    "link": "",
    "notes": "🔴 AutoScout Achado Kastenwagen <7k",
    "score": 52,
    "addedAt": "2026-03-21T13:21:16.640670"
  },
  {
    "id": "12860_0_2021",
    "vehicle": "Volkswagen up! ACTIVE",
    "price": 12860,
    "km": 0,
    "year": 2021,
    "fuel": "diesel",
    "source": "marketplace",
    "link": "",
    "notes": "🔴 AutoScout Achado Kastenwagen <7k",
    "score": 52,
    "addedAt": "2026-03-21T13:20:14.346210"
  },
  {
    "id": "11990_0_2021",
    "vehicle": "Dacia Spring Electric 65 Extreme",
    "price": 11990,
    "km": 0,
    "year": 2021,
    "fuel": "diesel",
    "source": "marketplace",
    "link": "",
    "notes": "🔴 AutoScout Achado Kastenwagen <7k",
    "score": 52,
    "addedAt": "2026-03-21T13:20:14.345205"
  },
  {
    "id": "12450_0_2021",
    "vehicle": "Opel Corsa Edition 1.2 Start/Stop",
    "price": 12450,
    "km": 0,
    "year": 2021,
    "fuel": "diesel",
    "source": "marketplace",
    "link": "",
    "notes": "🔴 AutoScout Achado Kastenwagen <7k",
    "score": 52,
    "addedAt": "2026-03-21T13:20:14.345205"
  },
  {
    "id": "13980_0_2021",
    "vehicle": "Citroen C3 Aircross Plus 1.2 *Einparkhilfe*Klima*Navi",
    "price": 13980,
    "km": 0,
    "year": 2021,
    "fuel": "diesel",
    "source": "marketplace",
    "link": "",
    "notes": "🔴 AutoScout Achado Kastenwagen <7k",
    "score": 52,
    "addedAt": "2026-03-21T13:20:14.345205"
  },
  {
    "id": "14490_0_2021",
    "vehicle": "Opel Corsa-e Edition*Klimaautomatik*Licht-/Regensenso",
    "price": 14490,
    "km": 0,
    "year": 2021,
    "fuel": "diesel",
    "source": "marketplace",
    "link": "",
    "notes": "🔴 AutoScout Achado Kastenwagen <7k",
    "score": 52,
    "addedAt": "2026-03-21T13:20:14.345205"
  },
  {
    "id": "13880_0_2021",
    "vehicle": "SEAT Ibiza 1.0 TSI FR PDC CarPlay Navi SHZ",
    "price": 13880,
    "km": 0,
    "year": 2021,
    "fuel": "diesel",
    "source": "marketplace",
    "link": "",
    "notes": "🔴 AutoScout Achado Kastenwagen <7k",
    "score": 52,
    "addedAt": "2026-03-21T13:20:14.343202"
  },
  {
    "id": "14690_0_2021",
    "vehicle": "Fiat Panda Pop 1.0*KLIMA*PDC*RADIO*BLUETOOTH*",
    "price": 14690,
    "km": 0,
    "year": 2021,
    "fuel": "diesel",
    "source": "marketplace",
    "link": "",
    "notes": "🔴 AutoScout Achado Kastenwagen <7k",
    "score": 52,
    "addedAt": "2026-03-21T13:19:12.009666"
  },
  {
    "id": "14440_0_2021",
    "vehicle": "Citroen C4 PureTech 130 S&S Feel SHZ NAVI PDC LED",
    "price": 14440,
    "km": 0,
    "year": 2021,
    "fuel": "diesel",
    "source": "marketplace",
    "link": "",
    "notes": "🔴 AutoScout Achado Kastenwagen <7k",
    "score": 52,
    "addedAt": "2026-03-21T13:19:12.009103"
  },
  {
    "id": "11750_0_2021",
    "vehicle": "Dacia Spring Electric Klima PDC Tempomat",
    "price": 11750,
    "km": 0,
    "year": 2021,
    "fuel": "diesel",
    "source": "marketplace",
    "link": "",
    "notes": "🔴 AutoScout Achado Kastenwagen <7k",
    "score": 52,
    "addedAt": "2026-03-21T13:19:12.006969"
  }
]